pymodaq/__init__.py
pymodaq/dashboard.py
pymodaq/icon.ico
pymodaq/splash.png
pymodaq/control_modules/__init__.py
pymodaq/control_modules/daq_move.py
pymodaq/control_modules/daq_viewer.py
pymodaq/control_modules/daq_viewer_ui.py
pymodaq/control_modules/mocks.py
pymodaq/control_modules/move_utility_classes.py
pymodaq/control_modules/thread_commands.py
pymodaq/control_modules/ui_utils.py
pymodaq/control_modules/utils.py
pymodaq/control_modules/viewer_utility_classes.py
pymodaq/control_modules/daq_move_ui/__init__.py
pymodaq/control_modules/daq_move_ui/factory.py
pymodaq/control_modules/daq_move_ui/ui_base.py
pymodaq/control_modules/daq_move_ui/uis/__init__.py
pymodaq/control_modules/daq_move_ui/uis/binary.py
pymodaq/control_modules/daq_move_ui/uis/original.py
pymodaq/control_modules/daq_move_ui/uis/relative.py
pymodaq/control_modules/daq_move_ui/uis/simple.py
pymodaq/daq_utils/__init__.py
pymodaq/daq_utils/daq_utils.py
pymodaq/examples/__init__.py
pymodaq/examples/function_plotter.py
pymodaq/examples/nonlinearscanner.py
pymodaq/examples/qt_less_standalone_module.py
pymodaq/examples/tcp_client.py
pymodaq/examples/Labview_TCP_Client/DAQ_TCP_Client.aliases
pymodaq/examples/Labview_TCP_Client/DAQ_TCP_Client.lvlps
pymodaq/examples/Labview_TCP_Client/DAQ_TCP_Client.lvproj
pymodaq/examples/Labview_TCP_Client/DAQ_TCP_Client.vi
pymodaq/examples/Labview_TCP_Client/DAQ_TCP_Server_1Dgaussian.vi
pymodaq/examples/Labview_TCP_Client/DAQ_TCP_Server_2Dgaussian.vi
pymodaq/examples/Labview_TCP_Client/DAQ_TCP_read_cmd.vi
pymodaq/examples/Labview_TCP_Client/DAQ_TCP_read_float.vi
pymodaq/examples/Labview_TCP_Client/DAQ_TCP_read_int.vi
pymodaq/examples/Labview_TCP_Client/DAQ_TCP_send_data.vi
pymodaq/examples/Labview_TCP_Client/DAQ_TCP_send_int.vi
pymodaq/examples/Labview_TCP_Client/DAQ_TCP_send_scalar.vi
pymodaq/examples/Labview_TCP_Client/DAQ_TCP_send_string.vi
pymodaq/examples/Labview_TCP_Client/client_state.ctl
pymodaq/examples/Labview_TCP_Client/cmd_types.ctl
pymodaq-5.1.8.dist-info/METADATA
pymodaq-5.1.8.dist-info/WHEEL
pymodaq-5.1.8.dist-info/entry_points.txt
pymodaq-5.1.8.dist-info/licenses/LICENSE
pymodaq-5.1.8.dist-info/RECORD
