Metadata-Version: 2.4
Name: pymodaq
Version: 5.1.8
Summary: Modular Data Acquisition with Python
Project-URL: Homepage, http://pymodaq.cnrs.fr
Project-URL: Source, https://github.com/PyMoDAQ/PyMoDAQ
Project-URL: Tracker, https://github.com/PyMoDAQ/PyMoDAQ/issues
Author-email: Sébastien Weber <sebastien.weber@cemes.fr>
License: The MIT License (MIT)
License-File: LICENSE
Classifier: Development Status :: 5 - Production/Stable
Classifier: Environment :: Other Environment
Classifier: Intended Audience :: Science/Research
Classifier: License :: OSI Approved :: MIT License
Classifier: Natural Language :: English
Classifier: Operating System :: OS Independent
Classifier: Programming Language :: Python :: 3.9
Classifier: Programming Language :: Python :: 3.10
Classifier: Programming Language :: Python :: 3.11
Classifier: Programming Language :: Python :: 3.12
Classifier: Topic :: Scientific/Engineering :: Human Machine Interfaces
Classifier: Topic :: Scientific/Engineering :: Visualization
Classifier: Topic :: Software Development :: Libraries :: Python Modules
Classifier: Topic :: Software Development :: User Interfaces
Requires-Python: >=3.8
Requires-Dist: adaptive
Requires-Dist: bayesian-optimization>=2.0
Requires-Dist: pyleco>0.3; python_version >= '3.8'
Requires-Dist: pymodaq-data>=5.0.21
Requires-Dist: pymodaq-gui>=5.0.32
Requires-Dist: pymodaq-plugin-manager>=0.0.17
Requires-Dist: pymodaq-plugins-mock>=5.0.5
Requires-Dist: pymodaq-utils>=1.0.11
Requires-Dist: qtconsole
Requires-Dist: simple-pid
Provides-Extra: dev
Requires-Dist: flake8; extra == 'dev'
Requires-Dist: h5py; extra == 'dev'
Requires-Dist: hatch; extra == 'dev'
Requires-Dist: pyqt5; extra == 'dev'
Requires-Dist: pyqt6; extra == 'dev'
Requires-Dist: pyside6; extra == 'dev'
Requires-Dist: pytest; extra == 'dev'
Requires-Dist: pytest-cov; extra == 'dev'
Requires-Dist: pytest-qt; extra == 'dev'
Requires-Dist: pytest-xdist; extra == 'dev'
Requires-Dist: pytest-xvfb; extra == 'dev'
